thronetrader/__init__.py
thronetrader/requirements.txt
thronetrader/trader.py
thronetrader/DL_algorithms/gru_future.py
thronetrader/DL_algorithms/gru_model.py
thronetrader/DL_algorithms/lstm_future.py
thronetrader/DL_algorithms/lstm_model.py
thronetrader/DL_algorithms/steward.py
thronetrader/ML_algorithms/gradient_boosting.py
thronetrader/ML_algorithms/linear_regression.py
thronetrader/helper/logger.py
thronetrader/helper/squire.py
thronetrader/helper/wrapper.py
thronetrader/realtime/financial.py
thronetrader/realtime/insider.py
thronetrader/realtime/volume.py
thronetrader/strategies/bollinger_bands.py
thronetrader/strategies/breakout.py
thronetrader/strategies/crossover.py
thronetrader/strategies/macd.py
thronetrader/strategies/rsi.py
throne_trader-0.4.dist-info/LICENSE
throne_trader-0.4.dist-info/METADATA
throne_trader-0.4.dist-info/WHEEL
throne_trader-0.4.dist-info/top_level.txt
throne_trader-0.4.dist-info/RECORD
