Metadata-Version: 2.1
Name: throne-trader
Version: 0.4
Summary: Python module that provides collection of algorithms to analyze, categorize and predict stocks.
Author-email: Vignesh Sivanandha Rao <svignesh1793@gmail.com>
License: MIT License
Project-URL: Homepage, https://github.com/thevickypedia/throne-trader
Project-URL: Docs, https://thevickypedia.github.io/throne-trader
Project-URL: Source, https://github.com/thevickypedia/throne-trader
Project-URL: Bug Tracker, https://github.com/thevickypedia/throne-trader/issues
Project-URL: Release Notes, https://github.com/thevickypedia/throne-trader/blob/main/release_notes.rst
Keywords: investment,stock-prediction,stock-market
Classifier: Development Status :: 5 - Production/Stable
Classifier: Intended Audience :: Information Technology
Classifier: Topic :: Office/Business :: Financial :: Investment
Classifier: License :: OSI Approved :: MIT License
Classifier: Programming Language :: Python :: 3 :: Only
Classifier: Operating System :: OS Independent
Requires-Python: >=3.8
License-File: LICENSE
Requires-Dist: numpy
Requires-Dist: pandas
Requires-Dist: yfinance
Requires-Dist: tensorflow
Requires-Dist: matplotlib
Requires-Dist: scikit-learn
Requires-Dist: pyfinviz
Requires-Dist: block-stdout
Provides-Extra: dev
Requires-Dist: sphinx ==5.1.1 ; extra == 'dev'
Requires-Dist: pre-commit ; extra == 'dev'
Requires-Dist: recommonmark ; extra == 'dev'
Requires-Dist: pytest ; extra == 'dev'
